mpaas/__init__.py
mpaas/charter.py
mpaas/config_handler.py
mpaas/main.py
mpaas/mpaas_exceptions.py
mpaas/value_parser.py
mpaas/controllers/__init__.py
mpaas/controllers/base.py
mpaas/controllers/chart.py
mpaas/controllers/config.py
mpaas/controllers/museum.py
mpaas/controllers/project.py
mpaas/controllers/template.py
mpaas/controllers/value.py
mpaas/core/__init__.py
mpaas/core/exc.py
mpaas/core/version.py
mpaas/ext/__init__.py
mpaas/templates/__init__.py
mpaas/templates/command1.jinja2
mpaas/templates/context.jinja2
mpaas/templates/describe_config.jinja2
mpaas/templates/list/__init__.py
mpaas/templates/list/charts.jinja2
mpaas/templates/list/configs.jinja2
mpaas/templates/list/context.jinja2
mpaas/templates/list/links.jinja2
mpaas/templates/list/museum_charts.jinja2
mpaas/templates/list/projects.jinja2
mpaas/templates/list/templates.jinja2
mpaas/templates/list/values.jinja2
kompaas-0.1.8.dist-info/METADATA
kompaas-0.1.8.dist-info/WHEEL
kompaas-0.1.8.dist-info/entry_points.txt
kompaas-0.1.8.dist-info/top_level.txt
kompaas-0.1.8.dist-info/RECORD
