Metadata-Version: 2.1
Name: kompaas
Version: 0.1.8
Summary: CLI for helm chart customization and deployment
Home-page: UNKNOWN
Author: Paolo Sini
Author-email: paolo@ziosting.fr
License: MIT
Platform: UNKNOWN
Requires-Dist: cement
Requires-Dist: jinja2
Requires-Dist: pyyaml
Requires-Dist: colorlog
Requires-Dist: nested-lookup
